gpio_respi/__init__.py
gpio_respi/gpio_respi.py
gpio_respi/sg90.py
gpio_respi-1.0.6.data/data/requirements.txt
gpio_respi-1.0.6.dist-info/METADATA
gpio_respi-1.0.6.dist-info/WHEEL
gpio_respi-1.0.6.dist-info/top_level.txt
gpio_respi-1.0.6.dist-info/RECORD
