Metadata-Version: 2.1
Name: gpio_respi
Version: 1.0.6
Summary: respi_socket_gpio
Home-page: https://pypi.org/project/gpio_respi/
Author: zhubin
Author-email: zhu2000410@163.com
Classifier: Programming Language :: Python :: 3
Classifier: License :: OSI Approved :: MIT License
Classifier: Operating System :: OS Independent
Requires-Python: >=3.6
